listener/__init__.py
listener/core.py
listener/meta.py
listener/utils.py
listener/vad.py
listener/assets/silero_decoder_v5.onnx
listener/assets/silero_encoder_v5.onnx
py_listener-1.1.0.dist-info/licenses/LICENSE
py_listener-1.1.0.dist-info/METADATA
py_listener-1.1.0.dist-info/WHEEL
py_listener-1.1.0.dist-info/top_level.txt
py_listener-1.1.0.dist-info/RECORD
