Metadata-Version: 2.4
Name: py-listener
Version: 1.1.0
Summary: Real time speech to text
Home-page: https://github.com/n1teshy/py-listener
Author: Nitesh Yadav
Author-email: nitesh.txt@gmail.com
License: MIT
Keywords: speech-to-text,offline speech to text,stt
Platform: Posix; Windows
Classifier: Intended Audience :: Developers
Classifier: Programming Language :: Python
Classifier: Programming Language :: Python :: 3
Classifier: License :: OSI Approved :: MIT License
Classifier: Operating System :: OS Independent
Requires-Python: >=3.9
License-File: LICENSE
Requires-Dist: numpy
Requires-Dist: pynvml
Requires-Dist: onnxruntime
Requires-Dist: sounddevice
Requires-Dist: faster-whisper
Dynamic: author
Dynamic: author-email
Dynamic: classifier
Dynamic: description
Dynamic: description-content-type
Dynamic: home-page
Dynamic: keywords
Dynamic: license
Dynamic: license-file
Dynamic: platform
Dynamic: requires-dist
Dynamic: requires-python
Dynamic: summary
